[
  {
    "type": "declaration",
    "named": true,
    "subtypes": [
      {
        "type": "effect_decl",
        "named": true
      },
      {
        "type": "enum_definition",
        "named": true
      },
      {
        "type": "function_declaration",
        "named": true
      },
      {
        "type": "import_decl",
        "named": true
      },
      {
        "type": "mod_decl",
        "named": true
      },
      {
        "type": "struct_decl",
        "named": true
      },
      {
        "type": "trait_definition",
        "named": true
      },
      {
        "type": "trait_instance",
        "named": true
      },
      {
        "type": "type_alias_decl",
        "named": true
      }
    ]
  },
  {
    "type": "expression",
    "named": true,
    "subtypes": [
      {
        "type": "binary_expression",
        "named": true
      },
      {
        "type": "call_expression",
        "named": true
      },
      {
        "type": "datalog_expression",
        "named": true
      },
      {
        "type": "eff_handle_block",
        "named": true
      },
      {
        "type": "foreach_expression",
        "named": true
      },
      {
        "type": "identifier",
        "named": true
      },
      {
        "type": "if_expression",
        "named": true
      },
      {
        "type": "inject_expression",
        "named": true
      },
      {
        "type": "interpolated_string",
        "named": true
      },
      {
        "type": "literal",
        "named": true
      },
      {
        "type": "match_expression",
        "named": true
      },
      {
        "type": "parenthetical_expression",
        "named": true
      },
      {
        "type": "path",
        "named": true
      },
      {
        "type": "pipeline_expression",
        "named": true
      },
      {
        "type": "query_expression",
        "named": true
      },
      {
        "type": "record_field_access",
        "named": true
      },
      {
        "type": "tuple",
        "named": true
      }
    ]
  },
  {
    "type": "type",
    "named": true,
    "subtypes": [
      {
        "type": "applied_type",
        "named": true
      },
      {
        "type": "arrow",
        "named": true
      },
      {
        "type": "datalog_type",
        "named": true
      },
      {
        "type": "identifier",
        "named": true
      },
      {
        "type": "path",
        "named": true
      },
      {
        "type": "tuple_type",
        "named": true
      },
      {
        "type": "type_record",
        "named": true
      }
    ]
  },
  {
    "type": "annotation",
    "named": true,
    "fields": {},
    "children": {
      "multiple": true,
      "required": true,
      "types": [
        {
          "type": "argument_list",
          "named": true
        },
        {
          "type": "identifier",
          "named": true
        }
      ]
    }
  },
  {
    "type": "applied_type",
    "named": true,
    "fields": {
      "parameters": {
        "multiple": true,
        "required": true,
        "types": [
          {
            "type": ",",
            "named": false
          },
          {
            "type": "[",
            "named": false
          },
          {
            "type": "]",
            "named": false
          },
          {
            "type": "type",
            "named": true
          }
        ]
      },
      "type": {
        "multiple": false,
        "required": true,
        "types": [
          {
            "type": "identifier",
            "named": true
          },
          {
            "type": "path",
            "named": true
          }
        ]
      }
    }
  },
  {
    "type": "argument_list",
    "named": true,
    "fields": {},
    "children": {
      "multiple": true,
      "required": false,
      "types": [
        {
          "type": "expression",
          "named": true
        },
        {
          "type": "keyword_argument",
          "named": true
        }
      ]
    }
  },
  {
    "type": "arrow",
    "named": true,
    "fields": {
      "effect": {
        "multiple": false,
        "required": false,
        "types": [
          {
            "type": "eff_expr",
            "named": true
          }
        ]
      },
      "left": {
        "multiple": false,
        "required": true,
        "types": [
          {
            "type": "type",
            "named": true
          }
        ]
      },
      "right": {
        "multiple": false,
        "required": true,
        "types": [
          {
            "type": "type",
            "named": true
          }
        ]
      }
    }
  },
  {
    "type": "assignment",
    "named": true,
    "fields": {
      "effect": {
        "multiple": false,
        "required": false,
        "types": [
          {
            "type": "eff_expr",
            "named": true
          }
        ]
      },
      "left": {
        "multiple": false,
        "required": false,
        "types": [
          {
            "type": "pattern",
            "named": true
          }
        ]
      },
      "name": {
        "multiple": false,
        "required": false,
        "types": [
          {
            "type": "identifier",
            "named": true
          }
        ]
      },
      "params": {
        "multiple": true,
        "required": false,
        "types": [
          {
            "type": "(",
            "named": false
          },
          {
            "type": ")",
            "named": false
          },
          {
            "type": ",",
            "named": false
          },
          {
            "type": "fn_parameter",
            "named": true
          }
        ]
      },
      "result_type": {
        "multiple": false,
        "required": false,
        "types": [
          {
            "type": "type",
            "named": true
          }
        ]
      },
      "right": {
        "multiple": false,
        "required": true,
        "types": [
          {
            "type": "expression",
            "named": true
          }
        ]
      }
    }
  },
  {
    "type": "binary_expression",
    "named": true,
    "fields": {
      "left": {
        "multiple": false,
        "required": true,
        "types": [
          {
            "type": "expression",
            "named": true
          }
        ]
      },
      "operator": {
        "multiple": false,
        "required": true,
        "types": [
          {
            "type": "!=",
            "named": false
          },
          {
            "type": "%",
            "named": false
          },
          {
            "type": "&",
            "named": false
          },
          {
            "type": "&&",
            "named": false
          },
          {
            "type": "*",
            "named": false
          },
          {
            "type": "**",
            "named": false
          },
          {
            "type": "+",
            "named": false
          },
          {
            "type": "-",
            "named": false
          },
          {
            "type": "->",
            "named": false
          },
          {
            "type": "/",
            "named": false
          },
          {
            "type": "<",
            "named": false
          },
          {
            "type": "<=",
            "named": false
          },
          {
            "type": "==",
            "named": false
          },
          {
            "type": ">",
            "named": false
          },
          {
            "type": ">=",
            "named": false
          },
          {
            "type": ">>",
            "named": false
          },
          {
            "type": "^",
            "named": false
          },
          {
            "type": "|",
            "named": false
          },
          {
            "type": "||",
            "named": false
          }
        ]
      },
      "right": {
        "multiple": false,
        "required": true,
        "types": [
          {
            "type": "expression",
            "named": true
          }
        ]
      }
    }
  },
  {
    "type": "body",
    "named": true,
    "fields": {},
    "children": {
      "multiple": true,
      "required": true,
      "types": [
        {
          "type": "assignment",
          "named": true
        },
        {
          "type": "expression",
          "named": true
        }
      ]
    }
  },
  {
    "type": "boolean",
    "named": true,
    "fields": {}
  },
  {
    "type": "call_expression",
    "named": true,
    "fields": {
      "arguments": {
        "multiple": false,
        "required": true,
        "types": [
          {
            "type": "argument_list",
            "named": true
          }
        ]
      },
      "function": {
        "multiple": true,
        "required": true,
        "types": [
          {
            "type": "(",
            "named": false
          },
          {
            "type": ")",
            "named": false
          },
          {
            "type": "expression",
            "named": true
          }
        ]
      }
    }
  },
  {
    "type": "char",
    "named": true,
    "fields": {}
  },
  {
    "type": "datalog_expression",
    "named": true,
    "fields": {},
    "children": {
      "multiple": true,
      "required": false,
      "types": [
        {
          "type": "datalog_fact",
          "named": true
        },
        {
          "type": "datalog_rule",
          "named": true
        }
      ]
    }
  },
  {
    "type": "datalog_fact",
    "named": true,
    "fields": {},
    "children": {
      "multiple": false,
      "required": true,
      "types": [
        {
          "type": "relation_expression",
          "named": true
        }
      ]
    }
  },
  {
    "type": "datalog_rule",
    "named": true,
    "fields": {
      "body": {
        "multiple": true,
        "required": true,
        "types": [
          {
            "type": ",",
            "named": false
          },
          {
            "type": "relation_expression",
            "named": true
          }
        ]
      },
      "condition": {
        "multiple": false,
        "required": false,
        "types": [
          {
            "type": "expression",
            "named": true
          }
        ]
      },
      "head": {
        "multiple": false,
        "required": true,
        "types": [
          {
            "type": "relation_expression",
            "named": true
          }
        ]
      }
    }
  },
  {
    "type": "datalog_type",
    "named": true,
    "fields": {},
    "children": {
      "multiple": true,
      "required": true,
      "types": [
        {
          "type": "identifier",
          "named": true
        },
        {
          "type": "relation_expression",
          "named": true
        }
      ]
    }
  },
  {
    "type": "eff_expr",
    "named": true,
    "fields": {
      "left": {
        "multiple": false,
        "required": false,
        "types": [
          {
            "type": "eff_expr",
            "named": true
          }
        ]
      },
      "operator": {
        "multiple": false,
        "required": false,
        "types": [
          {
            "type": "+",
            "named": false
          },
          {
            "type": "-",
            "named": false
          }
        ]
      },
      "right": {
        "multiple": false,
        "required": false,
        "types": [
          {
            "type": "eff_expr",
            "named": true
          }
        ]
      }
    },
    "children": {
      "multiple": true,
      "required": false,
      "types": [
        {
          "type": "applied_type",
          "named": true
        },
        {
          "type": "identifier",
          "named": true
        },
        {
          "type": "path",
          "named": true
        }
      ]
    }
  },
  {
    "type": "eff_handle_block",
    "named": true,
    "fields": {},
    "children": {
      "multiple": true,
      "required": true,
      "types": [
        {
          "type": "body",
          "named": true
        },
        {
          "type": "function_declaration",
          "named": true
        },
        {
          "type": "identifier",
          "named": true
        },
        {
          "type": "path",
          "named": true
        }
      ]
    }
  },
  {
    "type": "effect_decl",
    "named": true,
    "fields": {
      "name": {
        "multiple": false,
        "required": true,
        "types": [
          {
            "type": "identifier",
            "named": true
          }
        ]
      }
    },
    "children": {
      "multiple": true,
      "required": false,
      "types": [
        {
          "type": "annotation",
          "named": true
        },
        {
          "type": "doc_comment",
          "named": true
        },
        {
          "type": "modifier",
          "named": true
        },
        {
          "type": "signature",
          "named": true
        }
      ]
    }
  },
  {
    "type": "enum_case",
    "named": true,
    "fields": {
      "name": {
        "multiple": false,
        "required": true,
        "types": [
          {
            "type": "identifier",
            "named": true
          }
        ]
      },
      "params": {
        "multiple": true,
        "required": false,
        "types": [
          {
            "type": "(",
            "named": false
          },
          {
            "type": ")",
            "named": false
          },
          {
            "type": ",",
            "named": false
          },
          {
            "type": "path",
            "named": true
          }
        ]
      },
      "result_type": {
        "multiple": false,
        "required": false,
        "types": [
          {
            "type": "type",
            "named": true
          }
        ]
      }
    }
  },
  {
    "type": "enum_definition",
    "named": true,
    "fields": {
      "name": {
        "multiple": false,
        "required": true,
        "types": [
          {
            "type": "identifier",
            "named": true
          }
        ]
      },
      "type_params": {
        "multiple": false,
        "required": false,
        "types": [
          {
            "type": "type_params",
            "named": true
          }
        ]
      }
    },
    "children": {
      "multiple": true,
      "required": true,
      "types": [
        {
          "type": "annotation",
          "named": true
        },
        {
          "type": "doc_comment",
          "named": true
        },
        {
          "type": "enum_case",
          "named": true
        },
        {
          "type": "modifier",
          "named": true
        },
        {
          "type": "type",
          "named": true
        }
      ]
    }
  },
  {
    "type": "enum_pattern",
    "named": true,
    "fields": {
      "case": {
        "multiple": true,
        "required": true,
        "types": [
          {
            "type": "(",
            "named": false
          },
          {
            "type": ")",
            "named": false
          },
          {
            "type": "pattern",
            "named": true
          }
        ]
      },
      "enum": {
        "multiple": false,
        "required": true,
        "types": [
          {
            "type": "identifier",
            "named": true
          },
          {
            "type": "path",
            "named": true
          }
        ]
      }
    }
  },
  {
    "type": "fn_parameter",
    "named": true,
    "fields": {
      "name": {
        "multiple": false,
        "required": true,
        "types": [
          {
            "type": "identifier",
            "named": true
          }
        ]
      },
      "type": {
        "multiple": false,
        "required": false,
        "types": [
          {
            "type": "type",
            "named": true
          }
        ]
      }
    }
  },
  {
    "type": "foreach_expression",
    "named": true,
    "fields": {
      "body": {
        "multiple": false,
        "required": true,
        "types": [
          {
            "type": "body",
            "named": true
          }
        ]
      },
      "iterable": {
        "multiple": false,
        "required": true,
        "types": [
          {
            "type": "identifier",
            "named": true
          },
          {
            "type": "path",
            "named": true
          }
        ]
      }
    },
    "children": {
      "multiple": true,
      "required": true,
      "types": [
        {
          "type": "identifier",
          "named": true
        }
      ]
    }
  },
  {
    "type": "function_declaration",
    "named": true,
    "fields": {
      "body": {
        "multiple": true,
        "required": true,
        "types": [
          {
            "type": "body",
            "named": true
          },
          {
            "type": "{",
            "named": false
          },
          {
            "type": "}",
            "named": false
          }
        ]
      },
      "effect": {
        "multiple": false,
        "required": false,
        "types": [
          {
            "type": "eff_expr",
            "named": true
          }
        ]
      },
      "name": {
        "multiple": false,
        "required": true,
        "types": [
          {
            "type": "identifier",
            "named": true
          }
        ]
      },
      "params": {
        "multiple": true,
        "required": true,
        "types": [
          {
            "type": "(",
            "named": false
          },
          {
            "type": ")",
            "named": false
          },
          {
            "type": ",",
            "named": false
          },
          {
            "type": "fn_parameter",
            "named": true
          }
        ]
      },
      "result_type": {
        "multiple": false,
        "required": false,
        "types": [
          {
            "type": "type",
            "named": true
          }
        ]
      },
      "signature": {
        "multiple": true,
        "required": true,
        "types": [
          {
            "type": "(",
            "named": false
          },
          {
            "type": ")",
            "named": false
          },
          {
            "type": ",",
            "named": false
          },
          {
            "type": ":",
            "named": false
          },
          {
            "type": "\\",
            "named": false
          },
          {
            "type": "def",
            "named": false
          },
          {
            "type": "eff_expr",
            "named": true
          },
          {
            "type": "fn_parameter",
            "named": true
          },
          {
            "type": "type",
            "named": true
          }
        ]
      }
    },
    "children": {
      "multiple": true,
      "required": false,
      "types": [
        {
          "type": "annotation",
          "named": true
        },
        {
          "type": "doc_comment",
          "named": true
        },
        {
          "type": "modifier",
          "named": true
        }
      ]
    }
  },
  {
    "type": "if_expression",
    "named": true,
    "fields": {
      "condition": {
        "multiple": true,
        "required": true,
        "types": [
          {
            "type": "(",
            "named": false
          },
          {
            "type": ")",
            "named": false
          },
          {
            "type": "expression",
            "named": true
          }
        ]
      },
      "left": {
        "multiple": false,
        "required": true,
        "types": [
          {
            "type": "body",
            "named": true
          }
        ]
      },
      "right": {
        "multiple": false,
        "required": true,
        "types": [
          {
            "type": "body",
            "named": true
          }
        ]
      }
    }
  },
  {
    "type": "import_decl",
    "named": true,
    "fields": {},
    "children": {
      "multiple": true,
      "required": true,
      "types": [
        {
          "type": "identifier",
          "named": true
        },
        {
          "type": "path",
          "named": true
        }
      ]
    }
  },
  {
    "type": "inject_expression",
    "named": true,
    "fields": {
      "facts": {
        "multiple": false,
        "required": true,
        "types": [
          {
            "type": "identifier",
            "named": true
          },
          {
            "type": "path",
            "named": true
          }
        ]
      },
      "relation": {
        "multiple": false,
        "required": true,
        "types": [
          {
            "type": "identifier",
            "named": true
          },
          {
            "type": "path",
            "named": true
          }
        ]
      }
    }
  },
  {
    "type": "interpolated_string",
    "named": true,
    "fields": {},
    "children": {
      "multiple": true,
      "required": true,
      "types": [
        {
          "type": "expression",
          "named": true
        },
        {
          "type": "string_fragment",
          "named": true
        }
      ]
    }
  },
  {
    "type": "keyword_argument",
    "named": true,
    "fields": {
      "name": {
        "multiple": false,
        "required": true,
        "types": [
          {
            "type": "identifier",
            "named": true
          }
        ]
      },
      "value": {
        "multiple": false,
        "required": true,
        "types": [
          {
            "type": "expression",
            "named": true
          }
        ]
      }
    }
  },
  {
    "type": "literal",
    "named": true,
    "fields": {},
    "children": {
      "multiple": false,
      "required": true,
      "types": [
        {
          "type": "boolean",
          "named": true
        },
        {
          "type": "char",
          "named": true
        },
        {
          "type": "number",
          "named": true
        },
        {
          "type": "string",
          "named": true
        }
      ]
    }
  },
  {
    "type": "match_case",
    "named": true,
    "fields": {
      "body": {
        "multiple": false,
        "required": true,
        "types": [
          {
            "type": "body",
            "named": true
          }
        ]
      },
      "guard": {
        "multiple": false,
        "required": false,
        "types": [
          {
            "type": "expression",
            "named": true
          }
        ]
      },
      "pattern": {
        "multiple": false,
        "required": true,
        "types": [
          {
            "type": "pattern",
            "named": true
          }
        ]
      }
    }
  },
  {
    "type": "match_expression",
    "named": true,
    "fields": {
      "value": {
        "multiple": false,
        "required": true,
        "types": [
          {
            "type": "expression",
            "named": true
          }
        ]
      }
    },
    "children": {
      "multiple": true,
      "required": true,
      "types": [
        {
          "type": "match_case",
          "named": true
        }
      ]
    }
  },
  {
    "type": "mod_decl",
    "named": true,
    "fields": {
      "name": {
        "multiple": false,
        "required": true,
        "types": [
          {
            "type": "identifier",
            "named": true
          }
        ]
      }
    },
    "children": {
      "multiple": true,
      "required": false,
      "types": [
        {
          "type": "annotation",
          "named": true
        },
        {
          "type": "declaration",
          "named": true
        },
        {
          "type": "doc_comment",
          "named": true
        },
        {
          "type": "modifier",
          "named": true
        }
      ]
    }
  },
  {
    "type": "modifier",
    "named": true,
    "fields": {}
  },
  {
    "type": "parenthetical_expression",
    "named": true,
    "fields": {},
    "children": {
      "multiple": false,
      "required": true,
      "types": [
        {
          "type": "expression",
          "named": true
        }
      ]
    }
  },
  {
    "type": "path",
    "named": true,
    "fields": {},
    "children": {
      "multiple": true,
      "required": true,
      "types": [
        {
          "type": "identifier",
          "named": true
        }
      ]
    }
  },
  {
    "type": "pattern",
    "named": true,
    "fields": {},
    "children": {
      "multiple": false,
      "required": true,
      "types": [
        {
          "type": "enum_pattern",
          "named": true
        },
        {
          "type": "identifier",
          "named": true
        },
        {
          "type": "literal",
          "named": true
        },
        {
          "type": "path",
          "named": true
        },
        {
          "type": "record_pattern",
          "named": true
        },
        {
          "type": "tuple_pattern",
          "named": true
        }
      ]
    }
  },
  {
    "type": "pipeline_expression",
    "named": true,
    "fields": {
      "left": {
        "multiple": false,
        "required": true,
        "types": [
          {
            "type": "expression",
            "named": true
          }
        ]
      },
      "operator": {
        "multiple": false,
        "required": true,
        "types": [
          {
            "type": "|>",
            "named": false
          }
        ]
      },
      "right": {
        "multiple": false,
        "required": true,
        "types": [
          {
            "type": "expression",
            "named": true
          }
        ]
      }
    }
  },
  {
    "type": "query_expression",
    "named": true,
    "fields": {
      "selection": {
        "multiple": false,
        "required": true,
        "types": [
          {
            "type": "query_selection",
            "named": true
          }
        ]
      },
      "sources": {
        "multiple": false,
        "required": true,
        "types": [
          {
            "type": "query_source",
            "named": true
          }
        ]
      }
    },
    "children": {
      "multiple": false,
      "required": true,
      "types": [
        {
          "type": "relation_expression",
          "named": true
        }
      ]
    }
  },
  {
    "type": "query_selection",
    "named": true,
    "fields": {},
    "children": {
      "multiple": true,
      "required": true,
      "types": [
        {
          "type": "identifier",
          "named": true
        }
      ]
    }
  },
  {
    "type": "query_source",
    "named": true,
    "fields": {},
    "children": {
      "multiple": true,
      "required": true,
      "types": [
        {
          "type": "identifier",
          "named": true
        }
      ]
    }
  },
  {
    "type": "record_field_access",
    "named": true,
    "fields": {
      "field": {
        "multiple": false,
        "required": true,
        "types": [
          {
            "type": "identifier",
            "named": true
          }
        ]
      },
      "record": {
        "multiple": true,
        "required": true,
        "types": [
          {
            "type": "(",
            "named": false
          },
          {
            "type": ")",
            "named": false
          },
          {
            "type": "expression",
            "named": true
          }
        ]
      }
    }
  },
  {
    "type": "record_pattern",
    "named": true,
    "fields": {
      "remainder": {
        "multiple": true,
        "required": false,
        "types": [
          {
            "type": "identifier",
            "named": true
          },
          {
            "type": "|",
            "named": false
          }
        ]
      }
    },
    "children": {
      "multiple": true,
      "required": true,
      "types": [
        {
          "type": "identifier",
          "named": true
        }
      ]
    }
  },
  {
    "type": "relation_expression",
    "named": true,
    "fields": {
      "name": {
        "multiple": false,
        "required": true,
        "types": [
          {
            "type": "identifier",
            "named": true
          }
        ]
      }
    },
    "children": {
      "multiple": true,
      "required": true,
      "types": [
        {
          "type": "expression",
          "named": true
        }
      ]
    }
  },
  {
    "type": "signature",
    "named": true,
    "fields": {
      "effect": {
        "multiple": false,
        "required": false,
        "types": [
          {
            "type": "eff_expr",
            "named": true
          }
        ]
      },
      "name": {
        "multiple": false,
        "required": true,
        "types": [
          {
            "type": "identifier",
            "named": true
          }
        ]
      },
      "params": {
        "multiple": true,
        "required": true,
        "types": [
          {
            "type": "(",
            "named": false
          },
          {
            "type": ")",
            "named": false
          },
          {
            "type": ",",
            "named": false
          },
          {
            "type": "fn_parameter",
            "named": true
          }
        ]
      },
      "result_type": {
        "multiple": false,
        "required": false,
        "types": [
          {
            "type": "type",
            "named": true
          }
        ]
      }
    },
    "children": {
      "multiple": true,
      "required": false,
      "types": [
        {
          "type": "annotation",
          "named": true
        },
        {
          "type": "doc_comment",
          "named": true
        },
        {
          "type": "modifier",
          "named": true
        }
      ]
    }
  },
  {
    "type": "source_file",
    "named": true,
    "root": true,
    "fields": {},
    "children": {
      "multiple": true,
      "required": false,
      "types": [
        {
          "type": "declaration",
          "named": true
        }
      ]
    }
  },
  {
    "type": "string",
    "named": true,
    "fields": {},
    "children": {
      "multiple": true,
      "required": false,
      "types": [
        {
          "type": "string_fragment",
          "named": true
        }
      ]
    }
  },
  {
    "type": "struct_decl",
    "named": true,
    "fields": {
      "name": {
        "multiple": false,
        "required": true,
        "types": [
          {
            "type": "identifier",
            "named": true
          }
        ]
      },
      "type_params": {
        "multiple": false,
        "required": false,
        "types": [
          {
            "type": "type_params",
            "named": true
          }
        ]
      }
    },
    "children": {
      "multiple": true,
      "required": true,
      "types": [
        {
          "type": "annotation",
          "named": true
        },
        {
          "type": "doc_comment",
          "named": true
        },
        {
          "type": "modifier",
          "named": true
        },
        {
          "type": "struct_field",
          "named": true
        }
      ]
    }
  },
  {
    "type": "struct_field",
    "named": true,
    "fields": {
      "name": {
        "multiple": false,
        "required": true,
        "types": [
          {
            "type": "identifier",
            "named": true
          }
        ]
      },
      "type": {
        "multiple": false,
        "required": true,
        "types": [
          {
            "type": "type",
            "named": true
          }
        ]
      }
    },
    "children": {
      "multiple": false,
      "required": false,
      "types": [
        {
          "type": "modifier",
          "named": true
        }
      ]
    }
  },
  {
    "type": "trait_associated_item",
    "named": true,
    "fields": {
      "bound": {
        "multiple": false,
        "required": false,
        "types": [
          {
            "type": "applied_type",
            "named": true
          },
          {
            "type": "identifier",
            "named": true
          },
          {
            "type": "path",
            "named": true
          }
        ]
      },
      "default": {
        "multiple": false,
        "required": false,
        "types": [
          {
            "type": "type",
            "named": true
          }
        ]
      },
      "left": {
        "multiple": false,
        "required": false,
        "types": [
          {
            "type": "applied_type",
            "named": true
          },
          {
            "type": "identifier",
            "named": true
          },
          {
            "type": "path",
            "named": true
          }
        ]
      },
      "name": {
        "multiple": false,
        "required": true,
        "types": [
          {
            "type": "identifier",
            "named": true
          }
        ]
      },
      "operator": {
        "multiple": false,
        "required": false,
        "types": [
          {
            "type": "+",
            "named": false
          }
        ]
      },
      "right": {
        "multiple": false,
        "required": false,
        "types": [
          {
            "type": "applied_type",
            "named": true
          },
          {
            "type": "identifier",
            "named": true
          },
          {
            "type": "path",
            "named": true
          }
        ]
      }
    }
  },
  {
    "type": "trait_constraint",
    "named": true,
    "fields": {
      "left": {
        "multiple": false,
        "required": true,
        "types": [
          {
            "type": "applied_type",
            "named": true
          }
        ]
      },
      "right": {
        "multiple": false,
        "required": true,
        "types": [
          {
            "type": "type",
            "named": true
          }
        ]
      }
    }
  },
  {
    "type": "trait_definition",
    "named": true,
    "fields": {
      "name": {
        "multiple": false,
        "required": true,
        "types": [
          {
            "type": "identifier",
            "named": true
          }
        ]
      },
      "type_params": {
        "multiple": false,
        "required": false,
        "types": [
          {
            "type": "type_params",
            "named": true
          }
        ]
      }
    },
    "children": {
      "multiple": true,
      "required": false,
      "types": [
        {
          "type": "annotation",
          "named": true
        },
        {
          "type": "applied_type",
          "named": true
        },
        {
          "type": "body",
          "named": true
        },
        {
          "type": "doc_comment",
          "named": true
        },
        {
          "type": "modifier",
          "named": true
        },
        {
          "type": "signature",
          "named": true
        },
        {
          "type": "trait_associated_item",
          "named": true
        },
        {
          "type": "trait_law",
          "named": true
        }
      ]
    }
  },
  {
    "type": "trait_instance",
    "named": true,
    "fields": {
      "for_type": {
        "multiple": false,
        "required": true,
        "types": [
          {
            "type": "applied_type",
            "named": true
          },
          {
            "type": "identifier",
            "named": true
          },
          {
            "type": "path",
            "named": true
          }
        ]
      },
      "trait": {
        "multiple": false,
        "required": true,
        "types": [
          {
            "type": "path",
            "named": true
          }
        ]
      }
    },
    "children": {
      "multiple": true,
      "required": false,
      "types": [
        {
          "type": "annotation",
          "named": true
        },
        {
          "type": "applied_type",
          "named": true
        },
        {
          "type": "doc_comment",
          "named": true
        },
        {
          "type": "function_declaration",
          "named": true
        },
        {
          "type": "modifier",
          "named": true
        },
        {
          "type": "trait_associated_item",
          "named": true
        },
        {
          "type": "trait_constraint",
          "named": true
        }
      ]
    }
  },
  {
    "type": "trait_law",
    "named": true,
    "fields": {
      "name": {
        "multiple": false,
        "required": true,
        "types": [
          {
            "type": "identifier",
            "named": true
          }
        ]
      }
    },
    "children": {
      "multiple": true,
      "required": true,
      "types": [
        {
          "type": "annotation",
          "named": true
        },
        {
          "type": "applied_type",
          "named": true
        },
        {
          "type": "doc_comment",
          "named": true
        },
        {
          "type": "expression",
          "named": true
        },
        {
          "type": "modifier",
          "named": true
        },
        {
          "type": "type_param",
          "named": true
        }
      ]
    }
  },
  {
    "type": "tuple",
    "named": true,
    "fields": {},
    "children": {
      "multiple": true,
      "required": true,
      "types": [
        {
          "type": "expression",
          "named": true
        }
      ]
    }
  },
  {
    "type": "tuple_pattern",
    "named": true,
    "fields": {},
    "children": {
      "multiple": true,
      "required": true,
      "types": [
        {
          "type": "pattern",
          "named": true
        }
      ]
    }
  },
  {
    "type": "tuple_type",
    "named": true,
    "fields": {},
    "children": {
      "multiple": true,
      "required": true,
      "types": [
        {
          "type": "type",
          "named": true
        }
      ]
    }
  },
  {
    "type": "type_alias_decl",
    "named": true,
    "fields": {
      "aliased_type": {
        "multiple": false,
        "required": true,
        "types": [
          {
            "type": "type",
            "named": true
          }
        ]
      },
      "name": {
        "multiple": false,
        "required": true,
        "types": [
          {
            "type": "identifier",
            "named": true
          }
        ]
      },
      "type_params": {
        "multiple": false,
        "required": false,
        "types": [
          {
            "type": "type_params",
            "named": true
          }
        ]
      }
    },
    "children": {
      "multiple": true,
      "required": false,
      "types": [
        {
          "type": "annotation",
          "named": true
        },
        {
          "type": "doc_comment",
          "named": true
        },
        {
          "type": "modifier",
          "named": true
        }
      ]
    }
  },
  {
    "type": "type_param",
    "named": true,
    "fields": {
      "bound": {
        "multiple": false,
        "required": false,
        "types": [
          {
            "type": "type",
            "named": true
          }
        ]
      },
      "default": {
        "multiple": false,
        "required": false,
        "types": [
          {
            "type": "type",
            "named": true
          }
        ]
      },
      "name": {
        "multiple": false,
        "required": true,
        "types": [
          {
            "type": "identifier",
            "named": true
          }
        ]
      }
    }
  },
  {
    "type": "type_params",
    "named": true,
    "fields": {},
    "children": {
      "multiple": true,
      "required": true,
      "types": [
        {
          "type": "type_param",
          "named": true
        }
      ]
    }
  },
  {
    "type": "type_record",
    "named": true,
    "fields": {},
    "children": {
      "multiple": true,
      "required": false,
      "types": [
        {
          "type": "type_record_field",
          "named": true
        }
      ]
    }
  },
  {
    "type": "type_record_field",
    "named": true,
    "fields": {
      "name": {
        "multiple": false,
        "required": true,
        "types": [
          {
            "type": "identifier",
            "named": true
          }
        ]
      },
      "type": {
        "multiple": false,
        "required": true,
        "types": [
          {
            "type": "type",
            "named": true
          }
        ]
      }
    }
  },
  {
    "type": "!=",
    "named": false
  },
  {
    "type": "\"",
    "named": false
  },
  {
    "type": "#",
    "named": false
  },
  {
    "type": "#{",
    "named": false
  },
  {
    "type": "$",
    "named": false
  },
  {
    "type": "${",
    "named": false
  },
  {
    "type": "%",
    "named": false
  },
  {
    "type": "&",
    "named": false
  },
  {
    "type": "&&",
    "named": false
  },
  {
    "type": "'",
    "named": false
  },
  {
    "type": "(",
    "named": false
  },
  {
    "type": ")",
    "named": false
  },
  {
    "type": "*",
    "named": false
  },
  {
    "type": "**",
    "named": false
  },
  {
    "type": "+",
    "named": false
  },
  {
    "type": ",",
    "named": false
  },
  {
    "type": "-",
    "named": false
  },
  {
    "type": "->",
    "named": false
  },
  {
    "type": ".",
    "named": false
  },
  {
    "type": "/",
    "named": false
  },
  {
    "type": ":",
    "named": false
  },
  {
    "type": ":-",
    "named": false
  },
  {
    "type": ";",
    "named": false
  },
  {
    "type": "<",
    "named": false
  },
  {
    "type": "<-",
    "named": false
  },
  {
    "type": "<=",
    "named": false
  },
  {
    "type": "=",
    "named": false
  },
  {
    "type": "==",
    "named": false
  },
  {
    "type": "=>",
    "named": false
  },
  {
    "type": ">",
    "named": false
  },
  {
    "type": ">=",
    "named": false
  },
  {
    "type": ">>",
    "named": false
  },
  {
    "type": "@",
    "named": false
  },
  {
    "type": "[",
    "named": false
  },
  {
    "type": "\\",
    "named": false
  },
  {
    "type": "]",
    "named": false
  },
  {
    "type": "^",
    "named": false
  },
  {
    "type": "alias",
    "named": false
  },
  {
    "type": "case",
    "named": false
  },
  {
    "type": "comment",
    "named": true,
    "extra": true
  },
  {
    "type": "def",
    "named": false
  },
  {
    "type": "doc_comment",
    "named": true
  },
  {
    "type": "eff",
    "named": false
  },
  {
    "type": "else",
    "named": false
  },
  {
    "type": "enum",
    "named": false
  },
  {
    "type": "false",
    "named": false
  },
  {
    "type": "final",
    "named": false
  },
  {
    "type": "forall",
    "named": false
  },
  {
    "type": "foreach",
    "named": false
  },
  {
    "type": "from",
    "named": false
  },
  {
    "type": "handler",
    "named": false
  },
  {
    "type": "identifier",
    "named": true
  },
  {
    "type": "if",
    "named": false
  },
  {
    "type": "import",
    "named": false
  },
  {
    "type": "inject",
    "named": false
  },
  {
    "type": "inline",
    "named": false
  },
  {
    "type": "instance",
    "named": false
  },
  {
    "type": "into",
    "named": false
  },
  {
    "type": "law",
    "named": false
  },
  {
    "type": "lawful",
    "named": false
  },
  {
    "type": "let",
    "named": false
  },
  {
    "type": "match",
    "named": false
  },
  {
    "type": "mod",
    "named": false
  },
  {
    "type": "mut",
    "named": false
  },
  {
    "type": "number",
    "named": true
  },
  {
    "type": "opaque",
    "named": false
  },
  {
    "type": "override",
    "named": false
  },
  {
    "type": "pub",
    "named": false
  },
  {
    "type": "query",
    "named": false
  },
  {
    "type": "run",
    "named": false
  },
  {
    "type": "sealed",
    "named": false
  },
  {
    "type": "select",
    "named": false
  },
  {
    "type": "string_fragment",
    "named": true
  },
  {
    "type": "struct",
    "named": false
  },
  {
    "type": "trait",
    "named": false
  },
  {
    "type": "true",
    "named": false
  },
  {
    "type": "type",
    "named": false
  },
  {
    "type": "use",
    "named": false
  },
  {
    "type": "where",
    "named": false
  },
  {
    "type": "with",
    "named": false
  },
  {
    "type": "{",
    "named": false
  },
  {
    "type": "|",
    "named": false
  },
  {
    "type": "|>",
    "named": false
  },
  {
    "type": "||",
    "named": false
  },
  {
    "type": "}",
    "named": false
  },
  {
    "type": "~",
    "named": false
  }
]